ohmqtt/__init__.py
ohmqtt/__main__.py
ohmqtt/client.py
ohmqtt/error.py
ohmqtt/handles.py
ohmqtt/logger.py
ohmqtt/mqtt_spec.py
ohmqtt/platform.py
ohmqtt/property.py
ohmqtt/protected.py
ohmqtt/py.typed
ohmqtt/serialization.py
ohmqtt/session.py
ohmqtt/subscriptions.py
ohmqtt/topic_alias.py
ohmqtt/topic_filter.py
ohmqtt/cli/__init__.py
ohmqtt/cli/common.py
ohmqtt/cli/publish.py
ohmqtt/cli/subscribe.py
ohmqtt/connection/__init__.py
ohmqtt/connection/address.py
ohmqtt/connection/decoder.py
ohmqtt/connection/fsm.py
ohmqtt/connection/handlers.py
ohmqtt/connection/keepalive.py
ohmqtt/connection/selector.py
ohmqtt/connection/timeout.py
ohmqtt/connection/types.py
ohmqtt/connection/ws_decoder.py
ohmqtt/connection/wslib.py
ohmqtt/connection/states/__init__.py
ohmqtt/connection/states/base.py
ohmqtt/connection/states/closed.py
ohmqtt/connection/states/closing.py
ohmqtt/connection/states/connected.py
ohmqtt/connection/states/connecting.py
ohmqtt/connection/states/mqtt_handshake_connack.py
ohmqtt/connection/states/mqtt_handshake_connect.py
ohmqtt/connection/states/reconnect_wait.py
ohmqtt/connection/states/shutdown.py
ohmqtt/connection/states/tls_handshake.py
ohmqtt/connection/states/websocket_handshake_request.py
ohmqtt/connection/states/websocket_handshake_response.py
ohmqtt/packet/__init__.py
ohmqtt/packet/auth.py
ohmqtt/packet/base.py
ohmqtt/packet/connect.py
ohmqtt/packet/ping.py
ohmqtt/packet/publish.py
ohmqtt/packet/subscribe.py
ohmqtt/persistence/__init__.py
ohmqtt/persistence/base.py
ohmqtt/persistence/in_memory.py
ohmqtt/persistence/sqlite.py
ohmqtt-1.1.3.dist-info/licenses/LICENSE
ohmqtt-1.1.3.dist-info/METADATA
ohmqtt-1.1.3.dist-info/WHEEL
ohmqtt-1.1.3.dist-info/top_level.txt
ohmqtt-1.1.3.dist-info/RECORD
