Metadata-Version: 2.4
Name: ohmqtt
Version: 1.1.3
Summary: Persistent MQTT 5.0 client
License-Expression: MIT
Project-URL: Homepage, https://github.com/ohmqtt/ohmqtt_python
Project-URL: Issues, https://github.com/ohmqtt/ohmqtt_python/issues
Classifier: Development Status :: 5 - Production/Stable
Classifier: Intended Audience :: Developers
Classifier: Natural Language :: English
Classifier: Operating System :: OS Independent
Classifier: Programming Language :: Python :: 3
Classifier: Programming Language :: Python :: 3.10
Classifier: Programming Language :: Python :: 3.11
Classifier: Programming Language :: Python :: 3.12
Classifier: Programming Language :: Python :: 3.13
Classifier: Programming Language :: Python :: 3.14
Classifier: Programming Language :: Python :: Free Threading :: 3 - Stable
Classifier: Programming Language :: Python :: Implementation :: CPython
Classifier: Topic :: Communications
Classifier: Topic :: Home Automation
Classifier: Topic :: Internet
Classifier: Typing :: Typed
Requires-Python: >=3.10
License-File: LICENSE
Requires-Dist: typing-extensions>=4.12.2; python_version < "3.11"
Dynamic: license-file
